botshot/__init__.py
botshot/apps.py
botshot/bots.py
botshot/models.py
botshot/serializers.py
botshot/tasks.py
botshot/urls.py
botshot/version.py
botshot/views.py
botshot/bootstrap/__init__.py.tpl
botshot/bootstrap/botshot_settings.py
botshot/bootstrap/celery.py.tpl
botshot/bootstrap/urls.py.tpl
botshot/bootstrap/views.py.tpl
botshot/bootstrap/bots/__init__.py.tpl
botshot/bootstrap/bots/default.yaml.tpl
botshot/bootstrap/templates/landing.html-tpl
botshot/core/__init__.py
botshot/core/chat_manager.py
botshot/core/config.py
botshot/core/context.py
botshot/core/conversation_filter.py
botshot/core/dialog.py
botshot/core/entity_query.py
botshot/core/entity_value.py
botshot/core/flow.py
botshot/core/interceptors.py
botshot/core/interface_factory.py
botshot/core/message_processor.py
botshot/core/persistence.py
botshot/core/scheduler.py
botshot/core/tests.py
botshot/core/tests_dialog.py
botshot/core/interfaces/__init__.py
botshot/core/interfaces/alexa.py
botshot/core/interfaces/facebook.py
botshot/core/interfaces/google.py
botshot/core/interfaces/microsoft.py
botshot/core/interfaces/nao.py
botshot/core/interfaces/telegram.py
botshot/core/interfaces/test.py
botshot/core/interfaces/adapter/__init__.py
botshot/core/interfaces/adapter/facebook.py
botshot/core/interfaces/adapter/message_adapter.py
botshot/core/interfaces/adapter/microsoft.py
botshot/core/interfaces/adapter/telegram.py
botshot/core/logging/__init__.py
botshot/core/logging/chatbase.py
botshot/core/logging/elastic.py
botshot/core/logging/logging_service.py
botshot/core/logging/test_recorder.py
botshot/core/parsing/__init__.py
botshot/core/parsing/botshot_extractor.py
botshot/core/parsing/date_utils.py
botshot/core/parsing/duckling_extractor.py
botshot/core/parsing/entity_extractor.py
botshot/core/parsing/golem_extractor.py
botshot/core/parsing/message_parser.py
botshot/core/parsing/raw_message.py
botshot/core/parsing/wit_extractor.py
botshot/core/responses/__init__.py
botshot/core/responses/buttons.py
botshot-0.1.4.dist-info/LICENSE
botshot-0.1.4.dist-info/METADATA
botshot-0.1.4.dist-info/WHEEL
botshot-0.1.4.dist-info/entry_points.txt
botshot-0.1.4.dist-info/top_level.txt
botshot-0.1.4.dist-info/RECORD
