Metadata-Version: 2.1
Name: botshot
Version: 0.1.4
Summary: A framework for creating stateful chatbots on Django.
Home-page: https://github.com/prihoda/botshot
Author: David Příhoda, Matúš Žilinec, Jakub Drdák
Author-email: david.prihoda@gmail.com, zilinec.m@gmail.com
License: GPL
Platform: UNKNOWN
Classifier: Development Status :: 4 - Beta
Classifier: Environment :: Web Environment
Classifier: Framework :: Django
Classifier: Intended Audience :: Developers
Classifier: License :: OSI Approved :: GNU General Public License v3 (GPLv3)
Classifier: Operating System :: OS Independent
Classifier: Programming Language :: Python
Classifier: Programming Language :: Python :: 3
Classifier: Programming Language :: Python :: 3.5
Classifier: Programming Language :: Python :: 3.6
Classifier: Topic :: Internet :: WWW/HTTP
Classifier: Topic :: Internet :: WWW/HTTP :: Dynamic Content
Classifier: Topic :: Communications :: Chat
Requires-Dist: django (>=2.1.5)
Requires-Dist: networkx
Requires-Dist: requests
Requires-Dist: six
Requires-Dist: sqlparse
Requires-Dist: wit (==4.3.0)
Requires-Dist: wheel
Requires-Dist: redis
Requires-Dist: Pillow
Requires-Dist: jsonfield
Requires-Dist: pytz
Requires-Dist: unidecode
Requires-Dist: emoji
Requires-Dist: elasticsearch
Requires-Dist: celery (>=4.1.1)
Requires-Dist: python-dateutil
Requires-Dist: pyyaml
Requires-Dist: djangorestframework
Requires-Dist: pytest
Requires-Dist: pytest-django
Requires-Dist: mock
